{
  "api": "/api2/json/cluster/resources",
  "response": {
    "data": [
      {
        "pool": "Arab",
        "id": "/pool/Arab",
        "type": "pool"
      },
      {
        "mem": 35409438,
        "status": "running",
        "diskread": 361472,
        "id": "qemu/100",
        "disk": 0,
        "name": "space-station",
        "netout": 968918,
        "netin": 2074980,
        "vmid": 100,
        "maxmem": 2147483648,
        "maxdisk": 34359738368,
        "maxcpu": 1,
        "cpu": 0.353614775180745,
        "uptime": 9931,
        "diskwrite": 0,
        "template": 0,
        "type": "qemu",
        "node": "cmp"
      },
      {
        "maxcpu": 1,
        "cpu": 0,
        "uptime": 0,
        "diskwrite": 0,
        "node": "cmp",
        "type": "qemu",
        "template": 0,
        "mem": 0,
        "diskread": 0,
        "status": "stopped",
        "id": "qemu/101",
        "disk": 0,
        "netout": 0,
        "netin": 0,
        "vmid": 101,
        "maxmem": 2147483648,
        "maxdisk": 34359738368,
        "name": "moon-station"
      },
      {
        "maxcpu": 1,
        "cpu": 0,
        "diskwrite": 0,
        "uptime": 0,
        "type": "lxc",
        "node": "cmp",
        "template": 0,
        "mem": 0,
        "status": "stopped",
        "diskread": 0,
        "disk": 0,
        "id": "lxc/102",
        "name": "TianGong",
        "maxdisk": 8589934592,
        "netout": 0,
        "maxmem": 536870912,
        "netin": 0,
        "vmid": 102
      },
      {
        "node": "cmp",
        "type": "lxc",
        "template": 0,
        "uptime": 7933,
        "diskwrite": 16384,
        "cpu": 0,
        "maxcpu": 1,
        "netin": 2428474,
        "netout": 1944,
        "maxmem": 536870912,
        "vmid": 103,
        "maxdisk": 8388009984,
        "name": "ShenZhou",
        "id": "lxc/103",
        "disk": 46723072,
        "diskread": 10866688,
        "status": "running",
        "mem": 3780608
      },
      {
        "disk": 2605244416,
        "id": "node/cmp",
        "maxdisk": 12615557120,
        "maxmem": 8348389376,
        "mem": 1405644800,
        "status": "online",
        "uptime": 321820,
        "type": "node",
        "node": "cmp",
        "level": "",
        "maxcpu": 4,
        "cpu": 0.125697609783983
      },
      {
        "id": "storage/cmp/local",
        "disk": 2605244416,
        "maxdisk": 12615557120,
        "shared": 0,
        "content": "vztmpl,backup,iso",
        "type": "storage",
        "node": "cmp",
        "storage": "local",
        "plugintype": "dir",
        "status": "available"
      },
      {
        "content": "rootdir,images",
        "type": "storage",
        "node": "cmp",
        "shared": 0,
        "maxdisk": 24154996736,
        "id": "storage/cmp/local-lvm",
        "disk": 693248406,
        "status": "available",
        "plugintype": "lvmthin",
        "storage": "local-lvm"
      },
      {
        "storage": "wormhole",
        "plugintype": "lvmthin",
        "status": "available",
        "id": "storage/cmp/wormhole",
        "disk": 693248406,
        "shared": 0,
        "maxdisk": 24154996736,
        "content": "rootdir,images",
        "type": "storage",
        "node": "cmp"
      }
    ]
  }
}
